smolmodels/__init__.py
smolmodels/callbacks.py
smolmodels/config.py
smolmodels/constraints.py
smolmodels/datasets.py
smolmodels/exceptions.py
smolmodels/fileio.py
smolmodels/internal/__init__.py
smolmodels/internal/agents.py
smolmodels/internal/chat_agents.py
smolmodels/internal/common/__init__.py
smolmodels/internal/common/datasets/__init__.py
smolmodels/internal/common/datasets/adapter.py
smolmodels/internal/common/datasets/interface.py
smolmodels/internal/common/datasets/tabular.py
smolmodels/internal/common/provider.py
smolmodels/internal/common/registries/__init__.py
smolmodels/internal/common/registries/objects.py
smolmodels/internal/common/utils/__init__.py
smolmodels/internal/common/utils/agents.py
smolmodels/internal/common/utils/dataset_storage.py
smolmodels/internal/common/utils/dependency_utils.py
smolmodels/internal/common/utils/model_state.py
smolmodels/internal/common/utils/model_utils.py
smolmodels/internal/common/utils/pandas_utils.py
smolmodels/internal/common/utils/prompt_utils.py
smolmodels/internal/common/utils/pydantic_utils.py
smolmodels/internal/common/utils/response.py
smolmodels/internal/datasets/__init__.py
smolmodels/internal/datasets/config.py
smolmodels/internal/datasets/core/__init__.py
smolmodels/internal/datasets/core/generation/__init__.py
smolmodels/internal/datasets/core/generation/base.py
smolmodels/internal/datasets/core/generation/combined.py
smolmodels/internal/datasets/core/generation/simple_llm.py
smolmodels/internal/datasets/core/generation/utils/__init__.py
smolmodels/internal/datasets/core/generation/utils/oversampling.py
smolmodels/internal/datasets/core/validation/__init__.py
smolmodels/internal/datasets/core/validation/base.py
smolmodels/internal/datasets/core/validation/eda.py
smolmodels/internal/datasets/generator.py
smolmodels/internal/datasets/resources/templates/eda-notebook-tabular.ipynb
smolmodels/internal/models/__init__.py
smolmodels/internal/models/callbacks/__init__.py
smolmodels-0.15.0.dist-info/LICENSE
smolmodels-0.15.0.dist-info/METADATA
smolmodels-0.15.0.dist-info/WHEEL
smolmodels-0.15.0.dist-info/entry_points.txt
smolmodels-0.15.0.dist-info/RECORD
