Metadata-Version: 2.3
Name: smolmodels
Version: 0.15.0
Summary: An agentic framework for building ML models from natural language
License: Apache-2.0
Keywords: custom ai,llm,machine learning model,data generation
Author: marcellodebernardi
Author-email: marcello.debernardi@outlook.com
Requires-Python: >=3.11,<3.13
Classifier: Development Status :: 3 - Alpha
Classifier: Intended Audience :: Developers
Classifier: Intended Audience :: Science/Research
Classifier: License :: OSI Approved :: Apache Software License
Classifier: Programming Language :: Python :: 3
Classifier: Programming Language :: Python :: 3.11
Classifier: Programming Language :: Python :: 3.12
Classifier: Topic :: Scientific/Engineering :: Artificial Intelligence
Classifier: Topic :: Software Development :: Libraries :: Python Modules
Provides-Extra: all
Provides-Extra: deep-learning
Provides-Extra: lightweight
Requires-Dist: accelerate (==0.24.1) ; extra == "all" or extra == "deep-learning"
Requires-Dist: anthropic (==0.42.0)
Requires-Dist: bandit (>=1.8.2,<2.0.0)
Requires-Dist: black (>=24.10.0,<25.0.0)
Requires-Dist: dataclasses-json (>=0.6.7,<0.7.0)
Requires-Dist: google-generativeai (>=0.8.2,<0.9.0)
Requires-Dist: hypothesis (>=6.125.1,<7.0.0)
Requires-Dist: imbalanced-learn (>=0.12.4,<0.13.0)
Requires-Dist: instructor[anthropic] (>=1.7.2,<2.0.0)
Requires-Dist: jinja2 (>=3.1.6,<4.0.0)
Requires-Dist: joblib (>=1.4.2,<2.0.0)
Requires-Dist: litellm (>=1.65.4,<2.0.0)
Requires-Dist: mlflow (>=2.21.3,<3.0.0)
Requires-Dist: mlxtend (>=0.23.4,<0.24.0)
Requires-Dist: numpy (>=1.23.2,<2.0.0)
Requires-Dist: openai (>=1.60.1,<2.0.0)
Requires-Dist: pandas (>=2.2.0,<3.0.0)
Requires-Dist: platformdirs (>=4.3.7,<5.0.0)
Requires-Dist: pyarrow (>=19.0.0,<20.0.0)
Requires-Dist: pydantic (>=2.9.2,<3.0.0)
Requires-Dist: safetensors (>=0.4.1,<0.5.0) ; extra == "all" or extra == "deep-learning"
Requires-Dist: scikit-learn (>=1.5.2,<2.0.0)
Requires-Dist: seaborn (>=0.12.2,<0.13.0)
Requires-Dist: smolagents[gradio] (==1.13.0)
Requires-Dist: statsmodels (>=0.14.4,<0.15.0)
Requires-Dist: tenacity (>=9.0.0,<10.0.0)
Requires-Dist: tokenizers (>=0.15.1,<0.16.0) ; extra == "all" or extra == "deep-learning"
Requires-Dist: torch (>=2.0.0,<2.3.0) ; extra == "all" or extra == "deep-learning"
Requires-Dist: transformers (==4.35.2) ; extra == "all" or extra == "deep-learning"
Requires-Dist: xgboost (>=2.1.3,<3.0.0)
Project-URL: Homepage, https://github.com/plexe-ai/smolmodels
Project-URL: Repository, https://github.com/plexe-ai/smolmodels
